{"type":"Topology","arcs":[[[1755,557],[8,-54],[30,-38],[7,-94],[30,-70],[59,-14]],[[1889,287],[20,-42],[54,-165],[-213,84],[-344,-164],[-318,227],[-160,261],[-414,164]],[[514,652],[1,32],[74,63],[-15,34],[-58,34],[-7,28],[-65,48],[-48,25],[-6,24],[41,16],[11,32],[37,-10],[31,11],[27,33],[22,-33],[1,-46],[35,-11],[64,32],[27,-42],[29,20],[46,-23],[27,13],[39,-8],[31,-28],[16,19],[54,-11],[47,-26],[63,8],[44,-51],[135,-12],[7,64],[39,14],[49,-12],[19,19],[36,-36],[32,-117],[2,-141],[26,-26],[8,-56],[18,-24],[9,-62],[25,4],[19,62],[47,19],[26,-17],[70,-119],[35,23],[23,71],[34,63],[14,5]],[[1664,1966],[566,145],[38,-40],[13,-38],[67,-53],[118,-20],[1,-28],[34,-17],[-7,-59],[21,-44],[57,-87],[55,-43],[72,7],[29,-25],[-19,-58],[13,-22],[17,-73],[-18,-72],[1,-53],[-22,-34],[-72,0],[-49,23],[-38,-3],[-21,-27],[-20,-61],[-43,-9],[-15,-20],[-78,-20],[-17,-70],[6,-36],[-77,-40]],[[2276,1089],[-49,-19],[-25,-31],[-33,4],[-44,-31],[-40,16],[-64,1]],[[2021,1029],[-45,28],[-68,69],[-61,-85],[-35,25],[-18,67],[-70,66],[-25,-32],[-118,58],[-53,53],[-74,26]],[[1454,1304],[-34,19],[-3,47]],[[1417,1370],[46,14],[23,60],[61,25],[-22,68],[-54,69],[27,19],[25,42],[-23,33],[-1,34],[23,28],[142,204]],[[514,652],[-514,203],[0,517],[0,672],[53,31],[34,-29],[18,13],[82,-8],[70,-37],[95,-80],[16,-4],[54,-62],[82,-28],[16,42],[31,18],[49,-8],[59,13],[20,-41],[35,7],[36,-43],[56,41],[49,23],[106,-56],[16,-27],[40,-9]],[[1017,1800],[35,-60],[32,-23],[18,-64],[53,-40],[29,-40],[83,-27],[26,-21],[16,-103],[76,-2],[32,-50]],[[1454,1304],[13,-56],[-14,-88],[31,-2],[17,-49],[56,4],[20,-80],[46,-26],[-32,-21],[20,-76],[32,-43],[-2,-56],[16,-17],[45,-4],[60,11]],[[1762,801],[6,-51],[-21,-85],[19,-54],[-11,-54]],[[2021,1029],[-20,-58],[-33,-39],[-7,-32],[-49,-1],[-12,-15],[-81,-2],[-31,-29],[-26,-52]],[[1017,1800],[647,166]],[[2276,1089],[-14,-69],[16,-39],[-23,-49],[0,-29],[49,-56],[25,-1],[10,-42],[-26,-52],[56,-249],[-35,-34],[-32,10],[-77,-47],[-22,-52],[-29,8],[-20,30],[-52,15],[-28,-31],[-5,-45],[-22,-28],[-39,-8],[-15,21],[-75,8],[-29,-63]]],"transform":{"scale":[0.0005476899890470738,0.00045975747513028503],"translate":[142.75107900000012,-5.977772009999967]},"objects":{"png-districts-province-PG-EPW":{"type":"GeometryCollection","geometries":[{"arcs":[[0,1,2]],"type":"Polygon","properties":{"code":"PG-EPW-D001","name":"Kandep District","parent_code":"PG-EPW","admin_level":"2","admin_level_name":"district","country_code":"PNG","country_name":"Papua New Guinea","region_code":"HIGHLANDS","region_name":"Highlands Region","province_code":"PG-EPW","province_name":"Enga Province","district_code":"PG-EPW-D001","district_name":"Kandep District","source_code":"","source_name_column":"shapeName","source_code_column":"shapeISO"}},{"arcs":[[3,4,5,6,7]],"type":"Polygon","properties":{"code":"PG-EPW-D002","name":"Kompiam District","parent_code":"PG-EPW","admin_level":"2","admin_level_name":"district","country_code":"PNG","country_name":"Papua New Guinea","region_code":"HIGHLANDS","region_name":"Highlands Region","province_code":"PG-EPW","province_name":"Enga Province","district_code":"PG-EPW-D002","district_name":"Kompiam District","source_code":"","source_name_column":"shapeName","source_code_column":"shapeISO"}},{"arcs":[[-3,8,9,-7,10,11]],"type":"Polygon","properties":{"code":"PG-EPW-D003","name":"Lagaip/Pogera District","parent_code":"PG-EPW","admin_level":"2","admin_level_name":"district","country_code":"PNG","country_name":"Papua New Guinea","region_code":"HIGHLANDS","region_name":"Highlands Region","province_code":"PG-EPW","province_name":"Enga Province","district_code":"PG-EPW-D003","district_name":"Lagaip/Pogera District","source_code":"","source_name_column":"shapeName","source_code_column":"shapeISO"}},{"arcs":[[[-6,12,-11]],[[-8,-10,13]]],"type":"MultiPolygon","properties":{"code":"PG-EPW-D004","name":"Wabag District","parent_code":"PG-EPW","admin_level":"2","admin_level_name":"district","country_code":"PNG","country_name":"Papua New Guinea","region_code":"HIGHLANDS","region_name":"Highlands Region","province_code":"PG-EPW","province_name":"Enga Province","district_code":"PG-EPW-D004","district_name":"Wabag District","source_code":"","source_name_column":"shapeName","source_code_column":"shapeISO"}},{"arcs":[[-1,-12,-13,-5,14]],"type":"Polygon","properties":{"code":"PG-EPW-D005","name":"Wapenamanda District","parent_code":"PG-EPW","admin_level":"2","admin_level_name":"district","country_code":"PNG","country_name":"Papua New Guinea","region_code":"HIGHLANDS","region_name":"Highlands Region","province_code":"PG-EPW","province_name":"Enga Province","district_code":"PG-EPW-D005","district_name":"Wapenamanda District","source_code":"","source_name_column":"shapeName","source_code_column":"shapeISO"}}]}}}