{"type":"Topology","arcs":[[[1279,0],[-392,0],[-172,38],[-2,117],[-174,152]],[[539,307],[42,127],[-3,90],[-45,63],[-77,28],[-48,111],[-4,176]],[[404,902],[84,70],[6,97],[138,98],[42,-38],[113,28],[23,-145],[-27,-98],[-98,-48],[123,-86],[73,44],[-7,-98],[-60,-101],[129,-158],[336,-467]],[[1441,1507],[32,-72],[-14,-73],[18,-124],[-76,-55],[-116,0]],[[1285,1183],[-2,52],[-218,0],[-4,72],[-85,149]],[[976,1456],[228,66],[79,-10]],[[1283,1512],[33,-32],[125,27]],[[404,902],[-61,59]],[[343,961],[-24,66],[163,266],[26,199],[87,31]],[[595,1523],[-27,-83],[51,-87],[176,16],[90,-96]],[[885,1273],[-36,-100]],[[849,1173],[2,-237],[61,-64],[12,-94],[45,-44],[16,-167],[62,-97],[81,-22],[146,-178],[31,-103],[54,-11],[8,-89],[113,-13],[64,-54],[-265,0]],[[976,1456],[-115,109],[-127,19]],[[734,1584],[-81,63],[-110,186]],[[543,1833],[131,105]],[[674,1938],[57,-6],[97,-85],[77,-25],[98,-88],[90,17],[24,48],[157,-194],[9,-93]],[[885,1273],[66,-87]],[[951,1186],[-102,-13]],[[343,961],[-127,89]],[[216,1050],[-30,109],[33,33],[75,454],[-115,87],[-85,100],[449,0]],[[734,1584],[-111,1],[-28,-62]],[[539,307],[-59,52],[-198,50],[-23,23],[-11,132],[-248,219],[68,61],[71,-27],[13,118],[64,115]],[[1285,1183],[-39,-34],[-92,24],[-32,-26],[-171,39]],[[674,1938],[54,43],[67,-2],[91,-91],[150,-19],[28,36],[131,-45],[84,-78],[70,-118],[16,-65],[76,-92]],[[1430,2327],[71,-59],[52,-9],[82,-105],[-21,-110],[-41,-58],[-99,90],[-65,119],[21,132]]],"transform":{"scale":[0.0014540876950998472,0.0010910136414790884],"translate":[145.71146196000007,-7.998573959999931]},"objects":{"png-districts-province-PG-MPL":{"type":"GeometryCollection","geometries":[{"arcs":[[0,1,2]],"type":"Polygon","properties":{"code":"PG-MPL-D001","name":"Bulolo District","parent_code":"PG-MPL","admin_level":"2","admin_level_name":"district","country_code":"PNG","country_name":"Papua New Guinea","region_code":"MOMASE","region_name":"Momase Region","province_code":"PG-MPL","province_name":"Morobe Province","district_code":"PG-MPL-D001","district_name":"Bulolo District","source_code":"","source_name_column":"shapeName","source_code_column":"shapeISO"}},{"arcs":[[3,4,5,6]],"type":"Polygon","properties":{"code":"PG-MPL-D002","name":"Finschafen District","parent_code":"PG-MPL","admin_level":"2","admin_level_name":"district","country_code":"PNG","country_name":"Papua New Guinea","region_code":"MOMASE","region_name":"Momase Region","province_code":"PG-MPL","province_name":"Morobe Province","district_code":"PG-MPL-D002","district_name":"Finschafen District","source_code":"","source_name_column":"shapeName","source_code_column":"shapeISO"}},{"arcs":[[-3,7,8,9,10,11]],"type":"Polygon","properties":{"code":"PG-MPL-D003","name":"Huon District","parent_code":"PG-MPL","admin_level":"2","admin_level_name":"district","country_code":"PNG","country_name":"Papua New Guinea","region_code":"MOMASE","region_name":"Momase Region","province_code":"PG-MPL","province_name":"Morobe Province","district_code":"PG-MPL-D003","district_name":"Huon District","source_code":"","source_name_column":"shapeName","source_code_column":"shapeISO"}},{"arcs":[[-6,12,13,14,15]],"type":"Polygon","properties":{"code":"PG-MPL-D004","name":"Kabwum District","parent_code":"PG-MPL","admin_level":"2","admin_level_name":"district","country_code":"PNG","country_name":"Papua New Guinea","region_code":"MOMASE","region_name":"Momase Region","province_code":"PG-MPL","province_name":"Morobe Province","district_code":"PG-MPL-D004","district_name":"Kabwum District","source_code":"","source_name_column":"shapeName","source_code_column":"shapeISO"}},{"arcs":[[-11,16,17]],"type":"Polygon","properties":{"code":"PG-MPL-D005","name":"Lae District","parent_code":"PG-MPL","admin_level":"2","admin_level_name":"district","country_code":"PNG","country_name":"Papua New Guinea","region_code":"MOMASE","region_name":"Momase Region","province_code":"PG-MPL","province_name":"Morobe Province","district_code":"PG-MPL-D005","district_name":"Lae District","source_code":"","source_name_column":"shapeName","source_code_column":"shapeISO"}},{"arcs":[[-9,18,19,-14,20]],"type":"Polygon","properties":{"code":"PG-MPL-D006","name":"Markham District","parent_code":"PG-MPL","admin_level":"2","admin_level_name":"district","country_code":"PNG","country_name":"Papua New Guinea","region_code":"MOMASE","region_name":"Momase Region","province_code":"PG-MPL","province_name":"Morobe Province","district_code":"PG-MPL-D006","district_name":"Markham District","source_code":"","source_name_column":"shapeName","source_code_column":"shapeISO"}},{"arcs":[[-2,21,-19,-8]],"type":"Polygon","properties":{"code":"PG-MPL-D007","name":"Menyamya District","parent_code":"PG-MPL","admin_level":"2","admin_level_name":"district","country_code":"PNG","country_name":"Papua New Guinea","region_code":"MOMASE","region_name":"Momase Region","province_code":"PG-MPL","province_name":"Morobe Province","district_code":"PG-MPL-D007","district_name":"Menyamya District","source_code":"","source_name_column":"shapeName","source_code_column":"shapeISO"}},{"arcs":[[-5,22,-17,-10,-21,-13]],"type":"Polygon","properties":{"code":"PG-MPL-D008","name":"Nawae District","parent_code":"PG-MPL","admin_level":"2","admin_level_name":"district","country_code":"PNG","country_name":"Papua New Guinea","region_code":"MOMASE","region_name":"Momase Region","province_code":"PG-MPL","province_name":"Morobe Province","district_code":"PG-MPL-D008","district_name":"Nawae District","source_code":"","source_name_column":"shapeName","source_code_column":"shapeISO"}},{"arcs":[[[-7,-16,23]],[[24]]],"type":"MultiPolygon","properties":{"code":"PG-MPL-D009","name":"Tawae/Siassi District","parent_code":"PG-MPL","admin_level":"2","admin_level_name":"district","country_code":"PNG","country_name":"Papua New Guinea","region_code":"MOMASE","region_name":"Momase Region","province_code":"PG-MPL","province_name":"Morobe Province","district_code":"PG-MPL-D009","district_name":"Tawae/Siassi District","source_code":"","source_name_column":"shapeName","source_code_column":"shapeISO"}}]}}}