{"type":"Topology","arcs":[[[143,118],[-68,-118]],[[75,0],[-74,93]],[[1,93],[1,2]],[[2,95],[83,-26],[58,49]],[[2,95],[18,59],[58,13],[65,-49]],[[75,0],[-75,3],[1,90]]],"transform":{"scale":[0.0017084065104897928,0.00141506568862254],"translate":[145.13441508000005,-6.085621979999928]},"objects":{"png-llgs-district-PG-EHG-D001":{"type":"GeometryCollection","geometries":[{"arcs":[[0,1,2,3]],"type":"Polygon","properties":{"code":"PG-EHG-D001-L001","name":"Lower Asaro Rural LLG","parent_code":"PG-EHG-D001","admin_level":"3","admin_level_name":"llg","country_code":"PNG","country_name":"Papua New Guinea","region_code":"HIGHLANDS","region_name":"Highlands Region","province_code":"PG-EHG","province_name":"Eastern Highlands Province","district_code":"PG-EHG-D001","district_name":"Daulo District","llg_code":"PG-EHG-D001-L001","llg_name":"Lower Asaro Rural LLG","source_code":"","source_name_column":"shapeName","source_code_column":"shapeISO"}},{"arcs":[[-4,4]],"type":"Polygon","properties":{"code":"PG-EHG-D001-L002","name":"Upper Asaro Rural LLG","parent_code":"PG-EHG-D001","admin_level":"3","admin_level_name":"llg","country_code":"PNG","country_name":"Papua New Guinea","region_code":"HIGHLANDS","region_name":"Highlands Region","province_code":"PG-EHG","province_name":"Eastern Highlands Province","district_code":"PG-EHG-D001","district_name":"Daulo District","llg_code":"PG-EHG-D001-L002","llg_name":"Upper Asaro Rural LLG","source_code":"","source_name_column":"shapeName","source_code_column":"shapeISO"}},{"arcs":[[-2,5]],"type":"Polygon","properties":{"code":"PG-EHG-D001-L003","name":"Watabung Rural LLG","parent_code":"PG-EHG-D001","admin_level":"3","admin_level_name":"llg","country_code":"PNG","country_name":"Papua New Guinea","region_code":"HIGHLANDS","region_name":"Highlands Region","province_code":"PG-EHG","province_name":"Eastern Highlands Province","district_code":"PG-EHG-D001","district_name":"Daulo District","llg_code":"PG-EHG-D001-L003","llg_name":"Watabung Rural LLG","source_code":"","source_name_column":"shapeName","source_code_column":"shapeISO"}}]}}}