{"type":"Topology","arcs":[[[1772,698],[-75,0],[-44,-56],[-29,-14],[-26,-137]],[[1598,491],[-54,-15],[-40,12],[-46,-13],[-9,-62],[-161,12],[-52,49],[-74,-7],[-56,24],[-121,19],[-78,-4],[-55,22]],[[852,528],[8,25],[141,27],[17,29],[-28,78],[64,15],[10,111]],[[1064,813],[69,-20],[-2,-30],[40,-15],[88,13],[11,28],[66,-26],[55,9],[4,49],[49,9],[56,26],[59,136]],[[1559,992],[91,-2],[35,-41],[7,-53],[39,-18],[17,-54],[-17,-85],[37,-3],[4,-38]],[[1064,813],[-24,23],[22,48],[-70,27],[-24,25],[26,27],[-37,55],[-111,28],[-84,-6],[-55,29],[-18,27],[-91,48]],[[598,1144],[34,94],[6,60],[-38,75],[1,22]],[[601,1395],[19,41],[37,18],[58,-9],[70,13],[23,-40],[43,7],[42,-41],[126,61],[126,-53],[19,-27],[127,-89],[22,-62],[63,-37],[34,-40],[99,-26],[31,-20],[19,-99]],[[598,1144],[-62,-16],[1,-54],[60,-38],[33,-3],[23,-37],[-42,-61],[40,-19],[18,-111],[-74,-54],[0,-75],[52,-31],[-7,-40]],[[640,605],[-69,-42],[-45,9],[-54,-69],[135,-71],[7,-27],[70,-32],[18,-33],[-89,-61],[0,-31],[-613,196],[0,499],[0,649],[63,30],[40,-28],[22,13],[97,-8],[85,-36],[112,-77],[19,-4],[64,-59],[99,-28]],[[1772,698],[83,-5],[64,-195],[38,-42],[-2,-54],[73,-21],[71,10],[7,-48],[-25,-83],[23,-52],[-70,-118],[-28,-68],[-42,-22],[-83,115],[-31,16],[-56,-18],[-23,-60],[-29,-4],[-12,60],[-20,23],[-10,55],[-31,24],[-2,137],[-39,112],[-30,31]],[[852,528],[-35,-19],[-32,40],[-76,-30],[-42,10],[-1,44],[-26,32]]],"transform":{"scale":[0.00045977111111106803,0.0004760838532675971],"translate":[142.75107900000012,-5.796072989999971]},"objects":{"png-llgs-district-PG-EPW-D003":{"type":"GeometryCollection","geometries":[{"arcs":[[0,1,2,3,4]],"type":"Polygon","properties":{"code":"PG-EPW-D003-L001","name":"Lagaip Rural LLG","parent_code":"PG-EPW-D003","admin_level":"3","admin_level_name":"llg","country_code":"PNG","country_name":"Papua New Guinea","region_code":"HIGHLANDS","region_name":"Highlands Region","province_code":"PG-EPW","province_name":"Enga Province","district_code":"PG-EPW-D003","district_name":"Lagaip/Pogera District","llg_code":"PG-EPW-D003-L001","llg_name":"Lagaip Rural LLG","source_code":"","source_name_column":"shapeName","source_code_column":"shapeISO"}},{"arcs":[[-4,5,6,7]],"type":"Polygon","properties":{"code":"PG-EPW-D003-L002","name":"Maip Muritaka Rural LLG","parent_code":"PG-EPW-D003","admin_level":"3","admin_level_name":"llg","country_code":"PNG","country_name":"Papua New Guinea","region_code":"HIGHLANDS","region_name":"Highlands Region","province_code":"PG-EPW","province_name":"Enga Province","district_code":"PG-EPW-D003","district_name":"Lagaip/Pogera District","llg_code":"PG-EPW-D003-L002","llg_name":"Maip Muritaka Rural LLG","source_code":"","source_name_column":"shapeName","source_code_column":"shapeISO"}},{"arcs":[[-7,8,9]],"type":"Polygon","properties":{"code":"PG-EPW-D003-L003","name":"Paiela/Hewa Rural LLG","parent_code":"PG-EPW-D003","admin_level":"3","admin_level_name":"llg","country_code":"PNG","country_name":"Papua New Guinea","region_code":"HIGHLANDS","region_name":"Highlands Region","province_code":"PG-EPW","province_name":"Enga Province","district_code":"PG-EPW-D003","district_name":"Lagaip/Pogera District","llg_code":"PG-EPW-D003-L003","llg_name":"Paiela/Hewa Rural LLG","source_code":"","source_name_column":"shapeName","source_code_column":"shapeISO"}},{"arcs":[[-1,10]],"type":"Polygon","properties":{"code":"PG-EPW-D003-L004","name":"Pilikambi Rural LLG","parent_code":"PG-EPW-D003","admin_level":"3","admin_level_name":"llg","country_code":"PNG","country_name":"Papua New Guinea","region_code":"HIGHLANDS","region_name":"Highlands Region","province_code":"PG-EPW","province_name":"Enga Province","district_code":"PG-EPW-D003","district_name":"Lagaip/Pogera District","llg_code":"PG-EPW-D003-L004","llg_name":"Pilikambi Rural LLG","source_code":"","source_name_column":"shapeName","source_code_column":"shapeISO"}},{"arcs":[[-3,11,-9,-6]],"type":"Polygon","properties":{"code":"PG-EPW-D003-L005","name":"Porgera Rural LLG","parent_code":"PG-EPW-D003","admin_level":"3","admin_level_name":"llg","country_code":"PNG","country_name":"Papua New Guinea","region_code":"HIGHLANDS","region_name":"Highlands Region","province_code":"PG-EPW","province_name":"Enga Province","district_code":"PG-EPW-D003","district_name":"Lagaip/Pogera District","llg_code":"PG-EPW-D003-L005","llg_name":"Porgera Rural LLG","source_code":"","source_name_column":"shapeName","source_code_column":"shapeISO"}}]}}}