{"type":"Topology","arcs":[[[1013,653],[-215,-5],[-96,-26],[-9,-46],[20,-34],[12,-57],[-6,-36],[-50,-21],[-81,-19],[-18,12],[-35,7],[-29,-5],[-31,8]],[[475,431],[4,9],[-23,25],[3,25]],[[459,490],[24,-27],[15,17],[-33,17]],[[465,497],[15,19],[6,30],[-22,33],[-21,3],[-45,87]],[[398,669],[-67,159],[94,293],[14,-22],[12,-4],[9,-25],[19,-2],[22,-12],[3,-11],[26,-29],[-10,-9],[8,-32],[26,-13],[3,-19],[23,-10],[31,-25],[7,-23],[30,-1],[15,16],[31,-41],[0,-10],[319,-196]],[[1013,653],[-47,-234],[-85,-419],[-421,0],[-149,123]],[[311,123],[44,220]],[[355,343],[9,17],[111,71]],[[459,490],[6,7]],[[355,343],[-67,76],[-20,20]],[[268,439],[7,122],[123,108]],[[311,123],[-173,30],[-98,25],[-40,112],[56,63],[26,6],[186,80]]],"transform":{"scale":[0.0005259763474827858,0.000484664611953603],"translate":[145.60687584000004,-6.519157019999966]},"objects":{"png-llgs-district-PG-EHG-D004":{"type":"GeometryCollection","geometries":[{"arcs":[[0,1,2,3,4]],"type":"Polygon","properties":{"code":"PG-EHG-D004-L001","name":"Agarabi Rural LLG","parent_code":"PG-EHG-D004","admin_level":"3","admin_level_name":"llg","country_code":"PNG","country_name":"Papua New Guinea","region_code":"HIGHLANDS","region_name":"Highlands Region","province_code":"PG-EHG","province_name":"Eastern Highlands Province","district_code":"PG-EHG-D004","district_name":"Kainanatu District","llg_code":"PG-EHG-D004-L001","llg_name":"Agarabi Rural LLG","source_code":"","source_name_column":"shapeName","source_code_column":"shapeISO"}},{"arcs":[[-1,5,6,7]],"type":"Polygon","properties":{"code":"PG-EHG-D004-L002","name":"Gadsup/Tairora Rural LLG","parent_code":"PG-EHG-D004","admin_level":"3","admin_level_name":"llg","country_code":"PNG","country_name":"Papua New Guinea","region_code":"HIGHLANDS","region_name":"Highlands Region","province_code":"PG-EHG","province_name":"Eastern Highlands Province","district_code":"PG-EHG-D004","district_name":"Kainanatu District","llg_code":"PG-EHG-D004-L002","llg_name":"Gadsup/Tairora Rural LLG","source_code":"","source_name_column":"shapeName","source_code_column":"shapeISO"}},{"arcs":[[-3,8]],"type":"Polygon","properties":{"code":"PG-EHG-D004-L003","name":"Kainantu Urban LLG","parent_code":"PG-EHG-D004","admin_level":"3","admin_level_name":"llg","country_code":"PNG","country_name":"Papua New Guinea","region_code":"HIGHLANDS","region_name":"Highlands Region","province_code":"PG-EHG","province_name":"Eastern Highlands Province","district_code":"PG-EHG-D004","district_name":"Kainanatu District","llg_code":"PG-EHG-D004-L003","llg_name":"Kainantu Urban LLG","source_code":"","source_name_column":"shapeName","source_code_column":"shapeISO"}},{"arcs":[[-2,-8,9,10,-4,-9]],"type":"Polygon","properties":{"code":"PG-EHG-D004-L004","name":"Kamano No. 1 Rural LLG","parent_code":"PG-EHG-D004","admin_level":"3","admin_level_name":"llg","country_code":"PNG","country_name":"Papua New Guinea","region_code":"HIGHLANDS","region_name":"Highlands Region","province_code":"PG-EHG","province_name":"Eastern Highlands Province","district_code":"PG-EHG-D004","district_name":"Kainanatu District","llg_code":"PG-EHG-D004-L004","llg_name":"Kamano No. 1 Rural LLG","source_code":"","source_name_column":"shapeName","source_code_column":"shapeISO"}},{"arcs":[[-7,11,-10]],"type":"Polygon","properties":{"code":"PG-EHG-D004-L005","name":"Kamano No. 2 Rural LLG","parent_code":"PG-EHG-D004","admin_level":"3","admin_level_name":"llg","country_code":"PNG","country_name":"Papua New Guinea","region_code":"HIGHLANDS","region_name":"Highlands Region","province_code":"PG-EHG","province_name":"Eastern Highlands Province","district_code":"PG-EHG-D004","district_name":"Kainanatu District","llg_code":"PG-EHG-D004-L005","llg_name":"Kamano No. 2 Rural LLG","source_code":"","source_name_column":"shapeName","source_code_column":"shapeISO"}}]}}}